aiida_fleur/__init__.py
aiida_fleur/calculation/__init__.py
aiida_fleur/calculation/fleur.py
aiida_fleur/calculation/fleurinputgen.py
aiida_fleur/cmdline/__init__.py
aiida_fleur/cmdline/data/__init__.py
aiida_fleur/cmdline/data/fleurinp.py
aiida_fleur/cmdline/data/parameters.py
aiida_fleur/cmdline/data/structure.py
aiida_fleur/cmdline/launch/__init__.py
aiida_fleur/cmdline/launch/launch.py
aiida_fleur/cmdline/list/__init__.py
aiida_fleur/cmdline/util/__init__.py
aiida_fleur/cmdline/util/defaults.py
aiida_fleur/cmdline/util/options.py
aiida_fleur/cmdline/util/types.py
aiida_fleur/cmdline/util/utils.py
aiida_fleur/cmdline/visualization/__init__.py
aiida_fleur/cmdline/workflows/__init__.py
aiida_fleur/common/__init__.py
aiida_fleur/common/defaults.py
aiida_fleur/common/node_generators.py
aiida_fleur/data/__init__.py
aiida_fleur/data/fleurinp.py
aiida_fleur/data/fleurinpmodifier.py
aiida_fleur/parsers/__init__.py
aiida_fleur/parsers/fleur.py
aiida_fleur/parsers/fleur_inputgen.py
aiida_fleur/tools/StructureData_util.py
aiida_fleur/tools/__init__.py
aiida_fleur/tools/bfgs.py
aiida_fleur/tools/common_aiida.py
aiida_fleur/tools/common_fleur_wf.py
aiida_fleur/tools/common_fleur_wf_util.py
aiida_fleur/tools/create_corehole.py
aiida_fleur/tools/create_kpoints_from_distance.py
aiida_fleur/tools/data_handling.py
aiida_fleur/tools/dict_util.py
aiida_fleur/tools/element_econfig_list.py
aiida_fleur/tools/exp_bindingenergies.json
aiida_fleur/tools/extract_corelevels.py
aiida_fleur/tools/io_routines.py
aiida_fleur/tools/merge_parameter.py
aiida_fleur/tools/queue_defaults.py
aiida_fleur/tools/read_cif_folder.py
aiida_fleur/tools/straight_torque.py
aiida_fleur/tools/xml_aiida_modifiers.py
aiida_fleur/tools/plot/__init__.py
aiida_fleur/tools/plot/fleur.py
aiida_fleur/workflows/__init__.py
aiida_fleur/workflows/banddos.py
aiida_fleur/workflows/base_fleur.py
aiida_fleur/workflows/base_relax.py
aiida_fleur/workflows/cfcoeff.py
aiida_fleur/workflows/corehole.py
aiida_fleur-2.0.0.dist-info/entry_points.txt
aiida_fleur-2.0.0.dist-info/LICENSE
aiida_fleur-2.0.0.dist-info/WHEEL
aiida_fleur-2.0.0.dist-info/METADATA
aiida_fleur-2.0.0.dist-info/RECORD
