Metadata-Version: 2.1
Name: aiida-fleur
Version: 2.0.0
Summary: AiiDA Plugin for running the FLEUR code and its input generator. Also includes high-level workchains and utilities
Keywords: fleur,aiida,inpgen,workflows,flapw,juelich,dft,all-electron
Author-email: The JuDFT team <j.broeder@fz-juelich.de>
Requires-Python: >=3.8
Classifier: Framework :: AiiDA
Classifier: License :: OSI Approved :: MIT License
Classifier: Operating System :: POSIX :: Linux
Classifier: Operating System :: MacOS :: MacOS X
Classifier: Programming Language :: Python :: 3
Classifier: Programming Language :: Python :: 3.8
Classifier: Programming Language :: Python :: 3.9
Classifier: Programming Language :: Python :: 3.10
Classifier: Programming Language :: Python :: 3.11
Classifier: Environment :: Plugins
Classifier: Intended Audience :: Science/Research
Classifier: Topic :: Scientific/Engineering :: Physics
Classifier: Natural Language :: English
Requires-Dist: aiida-core[atomic_tools]>=2.0.1,<3.0.0
Requires-Dist: lxml~=4.8
Requires-Dist: numpy~=1.16,>=1.16.4
Requires-Dist: sympy
Requires-Dist: masci-tools~=0.13
Requires-Dist: future
Requires-Dist: pyhull
Requires-Dist: more_itertools
Requires-Dist: MarkupSafe<2.1.0
Requires-Dist: bumpver ; extra == "dev"
Requires-Dist: sphinx~=4.0 ; extra == "docs"
Requires-Dist: sphinx_rtd_theme ; extra == "docs"
Requires-Dist: sphinx-click ; extra == "docs"
Requires-Dist: myst-parser~=0.15.2 ; extra == "docs"
Requires-Dist: matplotlib ; extra == "graphs"
Requires-Dist: masci-tools[bokeh-plots] ; extra == "graphs"
Requires-Dist: pre-commit>=2.6.0 ; extra == "pre-commit"
Requires-Dist: yapf~=0.30 ; extra == "pre-commit"
Requires-Dist: pylint>=2.5 ; extra == "pre-commit"
Requires-Dist: mypy==0.990 ; extra == "pre-commit"
Requires-Dist: types-PyYAML ; extra == "pre-commit"
Requires-Dist: lxml-stubs~=0.4 ; extra == "pre-commit"
Requires-Dist: pytest>=2.9 ; extra == "testing"
Requires-Dist: pytest-timeout ; extra == "testing"
Requires-Dist: pytest-cov~=3.0 ; extra == "testing"
Requires-Dist: pytest-mpl>=0.12 ; extra == "testing"
Requires-Dist: pgtest ; extra == "testing"
Requires-Dist: pytest-regressions>=1.0 ; extra == "testing"
Project-URL: Documentation, https://aiida-fleur.readthedocs.io
Project-URL: Home, https://aiida-fleur..readthedocs.io
Project-URL: Source, https://github.com/JuDFTteam/aiida-fleur
Provides-Extra: dev
Provides-Extra: docs
Provides-Extra: graphs
Provides-Extra: pre-commit
Provides-Extra: testing
